transcriptor/__init__.py
transcriptor/alternatives.py
transcriptor/amazon.py
transcriptor/job.py
transcriptor/markers.py
transcriptor/speakers.py
transcriptor-2020.5.14.dist-info/LICENSE
transcriptor-2020.5.14.dist-info/METADATA
transcriptor-2020.5.14.dist-info/WHEEL
transcriptor-2020.5.14.dist-info/top_level.txt
transcriptor-2020.5.14.dist-info/RECORD
