Metadata-Version: 2.1
Name: transcriptor
Version: 2020.5.14
Summary: A wrapper for transcription results.
Home-page: https://github.com/kjaymiller/transcriptor
Author: Jay Miller
Author-email: kjaymiller@gmail.com
License: MIT
Platform: UNKNOWN
Requires-Dist: more-itertools
Requires-Dist: requests
